[
  {
    "title": "Test Title",
    "text": "Test text"
  },
  {
    "title": "Note ",
    "text": "Test n;lopt=",
    "id": "ce468dee-7570-40a3-bb86-06e0813be621"
  },
  {
    "title": "Transportation",
    "text": "Set up transportation for Tina on Friday the 29th of April ",
    "id": "84e41e63-39eb-49bf-b902-a2829ac64f43"
  },
  {
    "title": "Meeting ",
    "text": "Scheduled for Wednesday with Newborn team \nNeed to talk about new gifts for mom's at Metro. ",
    "id": "78f93812-fda0-450f-adf0-c6b939b3a03e"
  }
]